{
    "gmw-cfr": {
        "wiktionary_name": "Central Franconian"
    },
    "nds-de": {
        "wiktionary_name": "German Low German"
    },
    "gmw-jdt": {
        "wiktionary_name": "Jersey Dutch"
    },
    "grk-mar": {
        "wiktionary_name": "Mariupol Greek"
    },
    "zlw-ocs": {
        "wiktionary_name": "Old Czech"
    },
    "roa-opt": {
        "wiktionary_name": "Old Galician-Portuguese"
    },
    "zlw-opl": {
        "wiktionary_name": "Old Polish"
    },
    "map-pro": {
        "wiktionary_name": "Proto-Austronesian"
    },
    "cel-bry-pro": {
        "wiktionary_name": "Proto-Brythonic"
    },
    "gem-pro": {
        "wiktionary_name": "Proto-Germanic"
    },
    "jpx-pro": {
        "wiktionary_name": "Proto-Japonic"
    },
    "poz-mly-pro": {
        "wiktionary_name": "Proto-Malayic"
    },
    "poz-pro": {
        "wiktionary_name": "Proto-Malayo-Polynesian"
    },
    "jpx-ryu-pro": {
        "wiktionary_name": "Proto-Ryukyuan"
    },
    "gmq-scy": {
        "wiktionary_name": "Scanian"
    }
}